openavmkit/__init__.py
openavmkit/benchmark.py
openavmkit/calculations.py
openavmkit/checkpoint.py
openavmkit/cleaning.py
openavmkit/data.py
openavmkit/filters.py
openavmkit/horizontal_equity_study.py
openavmkit/income.py
openavmkit/inference.py
openavmkit/kolbe_et_al.py
openavmkit/land.py
openavmkit/modeling.py
openavmkit/pipeline.py
openavmkit/projection.py
openavmkit/quality_control.py
openavmkit/ratio_study.py
openavmkit/reports.py
openavmkit/sales_scrutiny_study.py
openavmkit/shap_analysis.py
openavmkit/time_adjustment.py
openavmkit/tuning.py
openavmkit/vertical_equity_study.py
openavmkit/cloud/__init__.py
openavmkit/cloud/azure.py
openavmkit/cloud/base.py
openavmkit/cloud/cloud.py
openavmkit/cloud/huggingface.py
openavmkit/cloud/sftp.py
openavmkit/resources/__init__.py
openavmkit/resources/reports/__init__.py
openavmkit/resources/reports/ratio_study.md
openavmkit/resources/reports/report.md
openavmkit/resources/reports/sales_scrutiny.md
openavmkit/resources/reports/variables.md
openavmkit/resources/reports/css/base.css
openavmkit/resources/reports/css/ratio_study.css
openavmkit/resources/reports/css/sales_scrutiny.css
openavmkit/resources/reports/css/variable.css
openavmkit/resources/settings/__init__.py
openavmkit/resources/settings/data_dictionary.json
openavmkit/resources/settings/settings.template.json
openavmkit/synthetic/__init__.py
openavmkit/synthetic/basic.py
openavmkit/synthetic/city.py
openavmkit/synthetic/generate.py
openavmkit/synthetic/synthetic.py
openavmkit/utilities/README.md
openavmkit/utilities/__init__.py
openavmkit/utilities/_utils.py
openavmkit/utilities/assertions.py
openavmkit/utilities/cache.py
openavmkit/utilities/census.py
openavmkit/utilities/clustering.py
openavmkit/utilities/data.py
openavmkit/utilities/excel.py
openavmkit/utilities/format.py
openavmkit/utilities/geometry.py
openavmkit/utilities/modeling.py
openavmkit/utilities/openstreetmap.py
openavmkit/utilities/overture.py
openavmkit/utilities/plotting.py
openavmkit-0.5.1.dist-info/METADATA
openavmkit-0.5.1.dist-info/WHEEL
openavmkit-0.5.1.dist-info/top_level.txt
openavmkit-0.5.1.dist-info/RECORD
